Workbook

Sheet README
A1: Batch 1 - Danalieth (niveau 59)
A2: Premier lot de contenu : tout ce que Danalieth utilise, au format d'import du catalogue.
A4: Onglets
A5: Entities : une ligne par élément du catalogue (classe, don, pouvoir, sort, objet, archétype...).
A6: Effects : un effet par ligne, rattaché à une entité par entity_id (modèle du moteur de règles).
A7: Progressions : une ligne par niveau de classe (BBA, sauvegardes, ce que le niveau donne).
A8: Relations : liens entre entités (donne, propriété d'objet, liste de sorts...).
A9: Danalieth checks : les 8 totaux de la fiche, recalculés à partir des composantes. Doivent rester à « OK ».
A10: Questions : ce que je n'ai pas pu déduire. Répondez dans la colonne jaune.
A12: Comment relire
A13: 1. Colonne status : draft = rempli par Claude, à relire ; to confirm = hypothèse à valider ; to complete = information manquante ; reviewed = validé par vous.
A14: 2. Cellules jaunes = à compléter ou confirmer en priorité.
... A23: Textes des livres hors SRD : résumés courts écrits par Claude, pas le texte du livre.

Sheet Questions
A1: # | B1: Topic | C1: Question | D1: Your answer | E1: Status
A2: 1 | B2: Fiche | C2: Base d'attaque : 39 dans le tableau des classes, 49 dans la ligne d'attaque. D'où viennent les 10 de plus ? | D2: Puissance divine : BBA = niveau jusqu'à 20, puis +0,75 par niveau (49 au niveau 59). Ajouté. | E2: answered (round 1)
A3: 2 | B3: Fiche | C3: Points de vie : 2480, puis −915, puis 1665. Que représente −915 ? | D3: Ignoré. | E3: answered (round 1)
A4: 3 | B4: Fiche | C4: Que représentent la ligne « 81 84 44 » et la valeur « 73,5 » à côté de Résistance suprême ? | D4: Totaux des jets de sauvegarde : recalculés dans Danalieth checks (81 / 84 / 44, OK). | E4: answered (round 1)
A5: 4 | B5: Fiche | C5: Ligne « Ward 4 3 » et « 8640 » : à quoi correspondent-ils ? | D5: Ward : 4 utilisations par jour (suivi des utilisations hors périmètre). 8640 ignoré. | E5: answered (round 1)
A6: 5 | B6: Fiche | C6: Caractéristiques : dans quelle colonne va chaque composante (base, race, Démon, Vampire, Dragon, tome, ioun, altération, sorts) ? L'export a perdu les colonnes vides. | D6: Colonnes = types de bonus. Tableau reconstruit dans Danalieth abilities, tous les totaux OK. | E6: answered (round 1)
A7: 6 | B7: Archétypes | C7: Démon, Vampire, Dragon : archétypes officiels (demi-fiélon, vampire, demi-dragon) ou de l'équipe ? Bonus de chacun ? | D7: Archétypes de l'équipe. | E7: answered (round 1)
A8: 7 | B8: Dons | C8: « 5 x spell improvement, caster level +4 » : quel don, quel effet par prise ? | D8: Don cumulable +4 niveau de lanceur, plafonné au niveau de personnage. | E8: answered (round 1)
A9: 8 | B9: Dons | C9: Superspell et Intensify : coût en niveaux d'emplacement, et mode des multiplicateurs (additif ou multiplicatif) ? | D9: Superspell ×4 : +9 ; Intensify ×2 : +6. | E9: answered (round 1)
A10: 9 | B10: Dons | C10: Attaque en puissance et Expertise du combat : valeur fixe à choisir dans l'app, ou description seule ? | D10: Interrupteur avec valeur choisie en début de tour. | E10: answered (round 1)
A11: 10 | B11: Volonté de la mort | C11: Art de la magie +5 / +10 / +20 et niveau de lanceur +3 / +6 / +15 : cumulatifs ou remplacements ? | D11: Remplacement. | E11: answered (round 1)
A12: 11 | B12: Volonté de la mort | C12: Sort épique : un sort connu en plus, ou un emplacement par jour en plus ? | D12: Un emplacement supplémentaire d'un niveau au-dessus du maximum. | E12: answered (round 1)
A13: 12 | B13: Sorts | C13: Moonbow, Météorite, Force du colosse, Force de la nature, Taille de géant, soins (375 et 40/round) : officiels ou de l'équipe ? Effets complets ? | D13: Colosse, Nature, Géant : officiels. Autres : équipe. | E13: answered (round 1)
... A34: 33 | B34: Mage ultime | C34: Niveaux 1 à 10 remplis de mémoire : à vérifier avec votre livre (onglet Progressions, lignes jaunes). | D34: Table du livre fournie, niveaux 1-10 remplis. | E34: answered (round 3)

Sheet Entities
A1: id | B1: type | C1: name_fr | D1: name_en | E1: provenance | F1: source | G1: labels | H1: prerequisite | I1: uses_per_day | J1: description_fr | K1: description_en | L1: status | M1: reviewer_notes
A2: feat.example_feat | B2: feat | C2: Nom français | D2: English name | E2: team | F2: Équipe | G2: melee; epic | H2: level() >= 21 | J2: Description courte en français. | K2: (later) | L2: draft | M2: Ligne d'exemple, ne pas importer
A3: class.warblade | B3: class | C3: Maître des lames | D3: Warblade | E3: official | F3: Book of Nine Swords | G3: melee; maneuvers | J3: Guerrier initiateur de manœuvres martiales ; d12, BBA élevé, Vigueur forte. | L3: draft | M3: Classe de base de Danalieth (niveaux 1-20).
A4: class.wizard | B4: class | C4: Magicien | D4: Wizard | E4: official | F4: SRD | G4: arcane; prepared | J4: Lanceur de sorts profanes préparés, d4. | L4: draft | M4: Mode de sorts : free slots (règle de campagne) ou prepared ? Voir Questions.
A5: class.sorcerer | B5: class | C5: Ensorceleur | D5: Sorcerer | E5: official | F5: SRD | G5: arcane; spontaneous | J5: Lanceur de sorts profanes spontanés, d4. | L5: draft
A6: class.archmage | B6: prestige_class | C6: Archimage | D6: Archmage | E6: official | F6: SRD | G6: arcane; epic-friendly | H6: Art de la magie 15 rangs ; sorts du 7e niveau ; Talent (Art de la magie) ; Science de... (voir SRD) | J6: Classe de prestige des maîtres des arcanes ; chaque niveau donne un pouvoir de Haute arcane. | L6: to confirm | M6: Prérequis exacts à reprendre du SRD lors de l'import.
A7: class.sevenfold_veil | B7: prestige_class | C7: Initié du voile septuple | D7: Initiate of the Sevenfold Veil | E7: official | F7: Complete Arcane | G7: arcane; abjuration | H7: @skill.knowledge_arcana.ranks >= 12 and @skill.knowledge_nature.ranks >= 4 and @skill.spellcraft.ranks >= 12 and has('feat.spell_focus_abjuration') and has('feat.greater_spell_focus_abjuration') and has('feat.skill_focus_spellcraft') | J7: Abjurateur qui tisse des voiles colorés. Dé de vie d4 ; 2 + Int points de compétence. Conditions : Connaissances (mystères) 12 rangs, Connaissances (nature) 4 rangs, Art de la magie 12 rangs, École renforcée et École supérieure (abjuration), Talent (Art de la magie), savoir lancer cinq sorts d'abjuration dont deux du 4e niveau ou plus. | L7: draft | M7: Source : dndtools.net. Condition « cinq sorts d'abjuration » vérifiée à la main.
A8: class.ultimate_magus | B8: prestige_class | C8: Mage ultime | D8: Ultimate Magus | E8: official + team | F8: Complete Mage + Équipe | G8: arcane; dual casting | J8: Combine magie préparée et spontanée, et utilise l'une pour renforcer l'autre. Dé de vie d4 ; 2 + Int points de compétence. Compétences de classe : Concentration, Artisanat, Décryptage, Connaissances (toutes), Profession, Art de la magie, Utilisation d'objets magiques. | L8: draft | M8: Niveaux 1-10 : table du livre (Complete Mage). Niveaux 11-20 : extension de l'équipe.
A9: class.vt_grip_of_death | B9: prestige_class | C9: Émissaire de Von Tarkhein : Poigne de la mort | D9: Emissary of Von Tarkhein: Grip of Death | E9: team | F9: Équipe | G9: death; melee; custom | J9: Voie martiale de l'émissaire : emprise sur la mort, résilience d'outre-tombe, régénération. | L9: draft | M9: Classe épique : BBA et sauvegardes +½ par niveau.
A10: class.vt_will_of_death | B10: prestige_class | C10: Émissaire de Von Tarkhein : Volonté de la mort | D10: Emissary of Von Tarkhein: Will of Death | E10: team | F10: Équipe | G10: death; arcane; custom | J10: Voie arcanique de l'émissaire : sorts épiques et secrets des arcanes. | L10: draft | M10: Classe épique : BBA et sauvegardes +½ par niveau. Danalieth : 3 niveaux.
A11: template.demon | B11: template | C11: Démon | D11: Demon | E11: team | F11: Équipe | G11: template; fiend | J11: Archétype démoniaque. | L11: draft | M11: Archétype de l'équipe. Bonus de caractéristiques repris de la fiche (onglet Danalieth abilities).
A12: template.vampire | B12: template | C12: Vampire | D12: Vampire | E12: team | F12: Équipe | G12: template; undead | J12: Archétype vampirique, avec règles maison (durée, critique, forme de chauve-souris). | L12: draft | M12: Archétype de l'équipe. Bonus de caractéristiques repris de la fiche (onglet Danalieth abilities).
A13: template.dragon | B13: template | C13: Dragon | D13: Dragon | E13: team | F13: Équipe | G13: template; dragon | J13: Archétype draconique. | L13: draft | M13: Archétype de l'équipe. Bonus de caractéristiques repris de la fiche (onglet Danalieth abilities).
A14: feat.spell_focus_abjuration | B14: feat | C14: École renforcée (abjuration) | D14: Spell Focus (abjuration) | E14: official | F14: SRD | G14: magic; DC | J14: +1 au DD des sorts d'abjuration. | L14: draft
A15: feat.greater_spell_focus_abjuration | B15: feat | C15: École supérieure (abjuration) | D15: Greater Spell Focus (abjuration) | E15: official | F15: SRD | G15: magic; DC | H15: has('feat.spell_focus_abjuration') | J15: +1 supplémentaire au DD des sorts d'abjuration. | L15: draft
A16: feat.skill_focus_spellcraft | B16: feat | C16: Talent (Art de la magie) | D16: Skill Focus (Spellcraft) | E16: official | F16: SRD | G16: skill | J16: +3 en Art de la magie. | L16: draft
A17: feat.power_attack | B17: feat | C17: Attaque en puissance | D17: Power Attack | E17: official | F17: SRD | G17: melee | H17: @ability.str.score >= 13 | J17: Échange un malus à l'attaque contre un bonus aux dégâts (double à deux mains). | L17: draft | M17: Interrupteur avec valeur choisie par le joueur en début de tour.
A18: feat.combat_expertise | B18: feat | C18: Expertise du combat | D18: Combat Expertise | E18: official | F18: SRD | G18: melee; defense | H18: @ability.int.score >= 13 | J18: Échange jusqu'à 5 points d'attaque contre la même valeur en CA (esquive). | L18: draft | M18: Interrupteur avec valeur choisie par le joueur en début de tour.
A19: feat.empower_spell | B19: feat | C19: Extension d'effet | D19: Empower Spell | E19: official | F19: SRD | G19: metamagic | J19: Effets numériques ×1,5 ; +2 niveaux d'emplacement. Non cumulable avec Empower, Intensify et Superspell : seul le plus fort s'applique. | L19: draft
A20: feat.quicken_spell | B20: feat | C20: Incantation rapide | D20: Quicken Spell | E20: official | F20: SRD | G20: metamagic | J20: Sort lancé par action rapide ; +4 niveaux. | L20: draft
A21: feat.extend_spell | B21: feat | C21: Extension de durée | D21: Extend Spell | E21: official | F21: SRD | G21: metamagic | J21: Durée ×2 ; +1 niveau. | L21: draft
A22: feat.persistent_spell | B22: feat | C22: Sort persistant | D22: Persistent Spell | E22: official | F22: Complete Arcane | G22: metamagic | J22: Durée portée à 24 heures ; +6 niveaux. | L22: to confirm | M22: Coût +6 d'après le livre ; à confirmer pour votre table.
A23: feat.intensify_spell | B23: feat | C23: Intensification | D23: Intensify Spell | E23: official | F23: Epic (SRD) | G23: metamagic; epic | J23: Effets numériques ×2 ; +6 niveaux d'emplacement (version de la table). Non cumulable avec Empower, Intensify et Superspell : seul le plus fort s'applique. | L23: draft
A24: feat.superspell | B24: feat | C24: Superspell | D24: Superspell | E24: team | F24: Équipe | G24: metamagic; custom | J24: Effets numériques ×4 (y compris les buffs : Force du taureau, Peau d'écorce...) ; +9 niveaux d'emplacement. Non cumulable avec Empower, Intensify et Superspell : seul le plus fort s'applique. | L24: draft
A25: feat.improved_metamagic | B25: feat | C25: Métamagie améliorée | D25: Improved Metamagic | E25: official | F25: Epic (SRD) | G25: metamagic; epic | J25: Réduit de 1 le coût de chaque don de métamagie (minimum +1). | L25: draft | M25: Peut être pris plusieurs fois dans le SRD épique.
A26: feat.improved_spell_capacity | B26: feat | C26: Capacité de sort améliorée | D26: Improved Spell Capacity | E26: official | F26: Epic (SRD) | G26: epic; slots | J26: Un emplacement d'un niveau au-dessus du maximum. Cumulable (×12 pour Danalieth). | L26: draft
A27: feat.spell_improvement | B27: feat | C27: Amélioration du niveau de lanceur | D27: Spell improvement | E27: to confirm | F27: to confirm | G27: epic; caster level | J27: +4 au niveau de lanceur par prise, sans dépasser le niveau de personnage. Cumulable ; sert aux multiclassés pour rattraper leur niveau de lanceur. | L27: draft | M27: Danalieth : 5 prises.
A28: feat.continuum_comprehension | B28: feat | C28: Compréhension du continuum | D28: Continuum Comprehension | E28: team | F28: Équipe | G28: skill; story | J28: +2 en Art de la magie. Obtenu quand le groupe a altéré le monde devant les elfes en lançant 1200 niveaux de sorts. | L28: draft
A29: power.warblade_battle_clarity | B29: class_power | C29: Clarté du combat | D29: Battle Clarity | E29: official | F29: Book of Nine Swords | G29: warblade | J29: Ajoute le modificateur d'Intelligence aux jets de Réflexes. | L29: to confirm | M29: Plafond par niveau de classe dans le livre ; règle maison sans plafond ?
A30: power.warblade_battle_cunning | B30: class_power | C30: Ruse du combat | D30: Battle Cunning | E30: official | F30: Book of Nine Swords + Équipe | G30: warblade | J30: Ajoute le modificateur d'Intelligence aux dégâts (règle maison : toujours, pas seulement contre un adversaire pris au dépourvu). | L30: to confirm
A31: power.warblade_battle_skill | B31: class_power | C31: Talent du combat | D31: Battle Skill | E31: official | F31: Book of Nine Swords | G31: warblade | J31: Ajoute le modificateur d'Intelligence aux tests opposés (bousculade, croc-en-jambe...). | L31: draft
A32: power.archmage_mastery_of_shaping | B32: class_power | C32: Maîtrise de la forme | D32: Mastery of Shaping | E32: official | F32: SRD | G32: archmage; high arcana | J32: Peut créer des espaces non affectés dans les cônes, cylindres, émanations, étendues et rayonnements. | L32: draft | M32: Description seule.
A33: power.archmage_mastery_of_elements | B33: class_power | C33: Maîtrise des énergies | D33: Mastery of Elements | E33: official | F33: SRD | G33: archmage; high arcana | J33: Change le type d'énergie d'un sort (acide, électricité, feu, froid, son). | L33: draft | M33: Description seule.
A34: power.archmage_mastery_of_counterspelling | B34: class_power | C34: Maîtrise des contresorts | D34: Mastery of Counterspelling | E34: official | F34: SRD | G34: archmage; high arcana | J34: Un sort contré est renvoyé au lieu d'être dissipé. | L34: draft | M34: Description seule.
A35: power.archmage_arcane_reach | B35: class_power | C35: Portée profane | D35: Arcane Reach | E35: official | F35: SRD | G35: archmage; high arcana | J35: Les sorts de contact peuvent être lancés à 9 m. | L35: draft | M35: Effet sur spell.range (set 9 m) quand la portée est contact.
A36: power.archmage_spell_power | B36: class_power | C36: Puissance des sorts | D36: Spell Power | E36: official | F36: SRD | G36: archmage; high arcana | J36: +1 niveau de lanceur de sorts. | L36: draft
A37: power.ultimate_magus_caster_level | B37: class_power | C37: Progression du mage ultime | D37: Ultimate Magus caster level | E37: official | F37: Complete Mage | G37: ultimate magus | J37: Fiche : niveau de lanceur +7 ; « Augmented 9 ». | L37: draft | M37: Fiche : « Caster level +7 ». Remplacé par Puissance des sorts profanes (+8 au niveau 20) et la progression des sorts ; à retirer si doublon.
A38: power.vt_grip_of_death | B38: class_power | C38: Emprise de la mort | D38: Grip of Death | E38: team | F38: Équipe | G38: death; aura | J38: Après 1 round d'activation (action libre), aura de 20 m : l'émissaire redirige sur lui 5 % des dégâts subis par ses alliés (10 % au niveau 2, 15 % au niveau 3). Cumulatif avec d'autres effets. | L38: draft
A39: power.vt_beyond_grave_resilience | B39: class_power | C39: Résilience d'outre-tombe | D39: Beyond-the-Grave Resilience | E39: team | F39: Équipe | G39: death; hit points | J39: +500 points de vie au niveau 1, 1000 au niveau 2, 2000 au total au niveau 3. | L39: draft
A40: power.vt_master_of_death | B40: class_power | C40: Maître de la mort | D40: Master of Death | E40: team | F40: Équipe | G40: death; regeneration | J40: Quand Emprise de la mort est active : régénération de 5 % du total de points de vie par round (10 %, puis 15 %). | L40: draft
A41: power.vt_arcane_secret_spellcraft | B41: class_power | C41: Secret des arcanes : Art de la magie | D41: Arcane Secret: Spellcraft | E41: team | F41: Équipe | G41: arcane | J41: Bonus en Art de la magie : +5, puis +10, puis +20. | L41: draft | M41: Remplacement (+20 au maximum), d'après votre réponse « je crois ».
A42: power.vt_mortis_incantatum | B42: class_power | C42: Mortis incantatum | D42: Mortis Incantatum | E42: team | F42: Équipe | G42: arcane; spell modifier | J42: Le sort gagne +10 niveau de lanceur pour passer la RM et +10 au DD ; la cible subit un malus à ses défenses égal à 1/4 du niveau du sort. | L42: draft | M42: Modificateur de sort (variante), sans coût d'emplacement.
A43: power.vt_primum_incantatum | B43: class_power | C43: Primum incantatum | D43: Primum Incantatum | E43: team | F43: Équipe | G43: arcane; spell modifier | J43: Dégâts du sort ×3, soins ×2, durée et zone ×2. | L43: draft | M43: Multiplicatif : se cumule avec la métamagie (Superspell ×4 puis ×3 = ×12).
A44: power.vt_infinitum_incantatum | B44: class_power | C44: Infinitum incantatum | D44: Infinitum Incantatum | E44: team | F44: Équipe | G44: arcane | J44: Lance un d10 : sur 8 ou moins, le sort lancé n'est pas consommé. | L44: draft | M44: Description seule (règle de table).
A45: power.vt_epic_spell | B45: class_power | C45: Sort épique (Volonté de la mort) | D45: Epic spell (Will of Death) | E45: team | F45: Équipe | G45: epic spell | J45: Un emplacement de sort supplémentaire d'un niveau au-dessus du maximum, aux niveaux 1, 3, 5, 8 et 10. | L45: draft
A46: power.vampire_bat_form | B46: class_power | C46: Forme de chauve-souris | D46: Bat form | E46: team | F46: Équipe | G46: vampire; form | J46: Forme de chauve-souris : enchaînement (50 % des dégâts) et +180 m de déplacement. | L46: to confirm | M46: 180 m de vol ou de déplacement au sol ?
A47: power.vampire_house_rules | B47: class_power | C47: Règles du vampire | D47: Vampire house rules | E47: team | F47: Équipe | G47: vampire | J47: Durée : niveau/3 + 3 ; bonus de critique (zone de critique +2 ou +3 ?). | L47: to confirm | M47: Fiche : « bonus critique (-2) » et lame « 3 vampire ».
A48: spell.bulls_strength | B48: spell | C48: Force du taureau | D48: Bull's Strength | E48: official | F48: SRD | G48: transmutation; buff | J48: +4 d'altération en Force. | L48: draft | M48: 16 sur la fiche = +4 × 4 (Superspell).
A49: spell.bears_endurance | B49: spell | C49: Endurance de l'ours | D49: Bear's Endurance | E49: official | F49: SRD | G49: transmutation; buff | J49: +4 d'altération en Constitution. | L49: draft | M49: 16 sur la fiche = +4 × 4 (Superspell).
A50: spell.foxs_cunning | B50: spell | C50: Ruse du renard | D50: Fox's Cunning | E50: official | F50: SRD | G50: transmutation; buff | J50: +4 d'altération en Intelligence. | L50: draft | M50: 16 sur la fiche = +4 × 4 (Superspell).
A51: spell.divine_favor | B51: spell | C51: Faveur divine | D51: Divine Favor | E51: official | F51: SRD (regles-donjons-dragons.com/page794.html) | G51: evocation; buff | J51: Bonus de chance de +1 aux jets d'attaque et de dégâts par tranche de 3 niveaux de lanceur (minimum +1, maximum +6). Ne s'applique pas aux dégâts des sorts. | L51: draft | M51: +24 = +6 × 4 (Superspell).
A52: spell.barkskin | B52: spell | C52: Peau d'écorce | D52: Barkskin | E52: official | F52: SRD | G52: transmutation; defense | J52: Bonus d'altération à l'armure naturelle : +2, +1 par 3 niveaux au-delà du 3e (max +5). | L52: draft | M52: Fiche : 20 = 5 × 4 avec Superspell, cohérent.
A53: spell.protection_from_evil | B53: spell | C53: Protection contre le Mal | D53: Protection from Evil | E53: official | F53: SRD | G53: abjuration; defense | J53: +2 de parade à la CA et +2 de résistance aux sauvegardes contre les créatures maléfiques. | L53: draft | M53: SRD (+2), fourni par l'Armure céleste.
A54: spell.force_of_colossus | B54: spell | C54: Force du colosse | D54: Force of the Colossus | E54: official | F54: to confirm (Spell Compendium ?) | G54: buff; strength | J54: Bonus de taille (+8 Force, +4 Constitution) ; l'arme passe à la taille G (épée à deux mains : 3d6). Règle de table : se cumule avec Taille de géant, et Danalieth le lance avec Empower (12 et 6). | L54: draft | M54: Accord du MJ.
A55: spell.force_of_nature | B55: spell | C55: Force de la nature | D55: Force of Nature | E55: official | F55: to confirm (Spell Compendium ?) | G55: buff | J55: +4 en Force, Dextérité et Constitution (16 avec Superspell). | L55: to confirm | M55: Officiel. Valeurs de base déduites de la fiche (÷ 4).
A56: spell.giant_size | B56: spell | C56: Taille de géant | D56: Giant Size | E56: official | F56: to confirm (Spell Compendium ?) | G56: buff; size | J56: Taille C (colossale) : bonus de taille correspondants, +32 en Force et +16 en Constitution. Règle de table : au niveau épique, le personnage gagne les attributs colossaux sans changer réellement de taille. | L56: draft | M56: Accord du MJ. Pas de Superspell sur ce sort.
A57: spell.moonbow | B57: spell | C57: Moonbow | D57: Moonbow | E57: team | F57: Équipe | G57: evocation; electricity; damage; rays | J57: Évocation 9 : trois rayons de 20d6 dégâts d'électricité. | L57: draft | M57: Liste de sorts (magicien/ensorceleur 9 ?) dans Relations.
A58: spell.meteorite | B58: spell | C58: Météorite | D58: Meteorite | E58: team | F58: Équipe | G58: evocation; fire; bludgeoning; damage; area | J58: Évocation 9 : 15 × 8d6 dégâts, moitié contondants, moitié feu, dans un rayon de 12 m. Pas de jet de sauvegarde. | L58: draft
A59: spell.heal_single | B59: spell | C59: Soin monocible (nom provisoire) | D59: Single-target heal (working name) | E59: team | F59: Équipe | G59: conjuration; healing | J59: Invocation (guérison), comparable à Guérison suprême de groupe mais sur une seule cible : 15 PV par niveau de lanceur, maximum 375. | L59: to confirm | M59: Nom définitif et niveau du sort ?
A60: spell.heal_over_time | B60: spell | C60: Soin sur la durée | D60: Heal over time | E60: team | F60: Équipe | G60: conjuration; healing | J60: Rend 40 PV par round pendant 1 round par niveau, maximum 30 rounds. | L60: to confirm | M60: Nom, école et niveau du sort ?
A61: item.blade_of_destruction | B61: item | C61: Lame de destruction | D61: Blade of Destruction | E61: team | F61: Équipe | G61: weapon; critical | J61: Arme +12 (épée à deux mains), critique 13-20 (base 19-20, +3 de l'arme, +3 du vampire), ×8 (×2 contre les immunisés). Sur un critique, on peut renoncer au multiplicateur pour : indomptabilité, lien de sang, ou Vigueur DD 10+2 par utilisation et −2 Constitution, critique automatique pendant 1 attaque. | L61: draft | M61: 13-20 confirmé (14-20 sur la fiche était une erreur).
A62: item.celestial_armor | B62: item | C62: Armure céleste | D62: Celestial Armor | E62: team | F62: Équipe | G62: armor | J62: Harnois +12 (20 en CA), Dextérité max 10, vol, immunité à la coercition. | L62: draft
A63: item.cloak_of_resistance_12 | B63: item | C63: Cape de résistance +12 | D63: Cloak of Resistance +12 | E63: official | F63: SRD (épique) | G63: cloak; saves | J63: +12 de résistance à tous les jets de sauvegarde. | L63: draft
A64: item.trinket_vampirism | B64: item | C64: Breloque de vampirisme | D64: Vampirism trinket | E64: team | F64: Équipe | G64: trinket; healing | J64: Soigne de la moitié des dégâts infligés, maximum la moitié des PV du personnage. Temps de recharge : 1d4−1. | L64: draft
A65: item.trinket_critical | B65: item | C65: Breloque critique | D65: Critical trinket | E65: team | F65: Équipe | G65: trinket; critical | J65: −4 sur le dé de critique (zone de critique +4) et +4 au multiplicateur de critique. Temps de recharge : 1d4+1. | L65: draft
A66: spell.divine_power | B66: spell | C66: Puissance divine | D66: Divine Power | E66: official | F66: SRD + Équipe | G66: evocation; buff; attack | J66: Règle maison : le BBA devient égal au niveau de personnage jusqu'au niveau 20, puis +0,75 par niveau au-delà (49 au niveau 59). +6 d'altération en Force (ne se cumule pas avec Force du taureau) et 1 PV temporaire par niveau. | L66: draft
A67: spell.spell_resistance | B67: spell | C67: Résistance à la magie | D67: Spell Resistance | E67: official | F67: SRD | G67: abjuration; defense | J67: RM égale à 12 + niveau de lanceur (72 avec niveau de lanceur 60). | L67: draft
A68: power.warblade_uncanny_dodge | B68: class_power | C68: Esquive instinctive | D68: Uncanny Dodge | E68: official | F68: Book of Nine Swords | G68: warblade; defense | J68: Ne peut pas être pris au dépourvu. | L68: draft | M68: « Unflooded » sur la fiche.
A69: power.ultimate_magus_augmented_casting_superior | B69: class_power | C69: Incantation augmentée supérieure | D69: Augmented Casting, Superior | E69: team | F69: Équipe | G69: ultimate magus; spells | J69: Comme Incantation augmentée, sans limite d'utilisation. Le sort sacrifié peut être remplacé par 2 sorts du niveau inférieur, 4 de deux niveaux en dessous ou 8 de trois niveaux en dessous ; les sacrifices se combinent (8 sorts du niveau 1 valent un sort du niveau 4). | L69: draft
A70: race.danalieth | B70: race | C70: Race personnalisée | D70: Custom race | E70: team | F70: Équipe | G70: race | J70: +2 Intelligence, −2 Charisme. | L70: draft | M70: Nom de la race à compléter.
A71: item.tomes | B71: item | C71: Tomes (+5) | D71: Tomes (+5) | E71: official | F71: SRD | G71: tome; inherent | J71: +5 inhérent en Force, Constitution, Intelligence et Charisme. | L71: draft | M71: Regroupés ; un tome par caractéristique dans le catalogue final.
A72: item.ioun_stones | B72: item | C72: Pierres ioun | D72: Ioun stones | E72: official | F72: SRD + Équipe | G72: ioun | J72: Pierres ioun standard. Règle de table : leur bonus d'altération se cumule avec l'altération normale, il devient donc son propre type (ioun). | L72: draft
A73: power.ultimate_magus_arcane_spell_power | B73: class_power | C73: Puissance des sorts profanes | D73: Arcane Spell Power | E73: official | F73: Complete Mage | G73: ultimate magus; caster level | J73: +1 au niveau de lanceur de tous les sorts profanes au niveau 1, puis +1 aux niveaux 4, 7 et 10 (+4). Extension de l'équipe : +5, +6, +7, +8 aux niveaux 12, 15, 18 et 20. | L73: draft
A74: power.ultimate_magus_augmented_casting | B74: class_power | C74: Incantation augmentée | D74: Augmented Casting | E74: official | F74: Complete Mage | G74: ultimate magus; spells | I74: 3 + floor(level('class.ultimate_magus') / 2) | J74: Dès le niveau 3 : sacrifier un sort ou un emplacement d'une classe pour appliquer un don de métamagie connu à un sort d'une autre classe profane. Niveau du sort augmenté ≤ ½ niveau de classe ; niveau de l'emplacement sacrifié ≥ ajustement du don ; impossible sur un sort déjà modifié par la métamagie. | L74: draft | M74: Remplacé par la version supérieure au niveau 20 (sans limite).
A75: power.ultimate_magus_expanded_knowledge | B75: class_power | C75: Connaissance des sorts étendue | D75: Expanded Spell Knowledge | E75: official | F75: Complete Mage | G75: ultimate magus; spells | J75: Aux niveaux 2, 4, 6, 8 et 10 : ajoute un sort du grimoire aux sorts connus d'une classe spontanée, même d'un niveau qu'elle ne peut pas encore lancer (niveau maximal : 1, 2, 3, 4 puis 5). | L75: draft
A76: power.ultimate_magus_bonus_feat | B76: class_power | C76: Don supplémentaire (métamagie) | D76: Bonus Feat (metamagic) | E76: official | F76: Complete Mage | G76: ultimate magus; metamagic | J76: Un don de métamagie supplémentaire dont le personnage remplit les conditions (niveaux 5 et 9 ; 13, 16 et 19 avec l'extension). | L76: draft
A77: power.vt_will_of_death_saves | B77: class_power | C77: Résistance de l'émissaire | D77: Emissary's resilience | E77: team | F77: Équipe | G77: death; saves | J77: Bonus aux trois jets de sauvegarde, ajouté pour retrouver les valeurs jouées à la table. | L77: draft | M77: Corrige l'ancienne erreur de calcul : 1,5 (règle épique) + 3,5 = 5 pour 3 niveaux.
A78: power.sv_warding | B78: class_power | C78: Protection | D78: Warding | E78: official | F78: Complete Arcane | G78: sevenfold veil; defense | I78: floor((level('class.sevenfold_veil') + 1) / 2) | J78: Crée une barrière portant un voile connu : personnelle (1 min/niveau), de zone (1 min/niveau) ou mur (10 min/niveau). DD 18 + modificateur de la caractéristique de lanceur ; niveau de lanceur profane. 1/jour, puis 2, 3 et 4/jour aux niveaux 3, 5 et 7. | L78: draft | M78: Les « wards » de la fiche.
A79: power.sv_veil_red | B79: class_power | C79: Voile rouge | D79: Red veil | E79: official | F79: Complete Arcane | G79: sevenfold veil; veil | J79: Bloque les attaques à distance non magiques. Le traverser inflige 20 dégâts de feu (Réflexes ½). Détruit par cône de froid. Obtenu au niveau 1. | L79: draft
A80: power.sv_veil_orange | B80: class_power | C80: Voile orange | D80: Orange veil | E80: official | F80: Complete Arcane | G80: sevenfold veil; veil | J80: Bloque les attaques à distance magiques (rayons, projectiles). Le traverser inflige 40 dégâts d'acide (Réflexes ½). Détruit par bourrasque. Obtenu au niveau 2. | L80: draft
A81: power.sv_veil_yellow | B81: class_power | C81: Voile jaune | D81: Yellow veil | E81: official | F81: Complete Arcane | G81: sevenfold veil; veil | J81: Bloque gaz, nuages et pétrification ; immunité au poison venu de l'extérieur. Le traverser inflige 80 dégâts d'électricité (Réflexes ½). Détruit par désintégration. Obtenu au niveau 3. | L81: draft
A82: power.sv_veil_green | B82: class_power | C82: Voile vert | D82: Green veil | E82: official | F82: Complete Arcane | G82: sevenfold veil; veil | J82: Bloque les souffles. Le traverser : Vigueur ou mort (réussite : 1d6 Constitution) ; effet de poison. Détruit par passe-muraille. Obtenu au niveau 4. | L82: draft
A83: power.sv_veil_blue | B83: class_power | C83: Voile bleu | D83: Blue veil | E83: official | F83: Complete Arcane | G83: sevenfold veil; veil | J83: Bloque divinations et effets mentaux. Le traverser : Vigueur ou pétrification. Détruit par projectile magique. Obtenu au niveau 5. | L83: draft
A84: power.sv_veil_indigo | B84: class_power | C84: Voile indigo | D84: Indigo veil | E84: official | F84: Complete Arcane | G84: sevenfold veil; veil | J84: Bloque sorts et pouvoirs magiques. Le traverser : Volonté ou confusion (comme aliénation mentale). Annulé par lumière du jour. Obtenu au niveau 6. | L84: draft
A85: power.sv_veil_violet | B85: class_power | C85: Voile violet | D85: Violet veil | E85: official | F85: Complete Arcane | G85: sevenfold veil; veil | J85: Désintègre objets et effets qui le traversent ; créatures : Volonté ou changement de plan aléatoire. Détruit par dissipation de la magie. Obtenu au niveau 7. | L85: draft
A86: power.sv_unimpeachable_abjuration | B86: class_power | C86: Abjuration inébranlable | D86: Unimpeachable Abjuration | E86: official | F86: Complete Arcane | G86: sevenfold veil; dispel | J86: Ajoute le niveau de classe au DD pour dissiper ses abjurations. | L86: draft | M86: Fiche : « DD dissipation +7 ».
A87: power.sv_unanswerable_strike | B87: class_power | C87: Frappe imparable | D87: Unanswerable Strike | E87: official | F87: Complete Arcane | G87: sevenfold veil; dispel | J87: +2 aux tests de niveau de lanceur pour contrer ou dissiper les abjurations (+4 au niveau 6). | L87: draft | M87: Fiche : « DD pour dissiper −4 ».
A88: power.sv_reactive_warding | B88: class_power | C88: Protection réactive | D88: Reactive Warding | E88: official | F88: Complete Arcane | G88: sevenfold veil; defense | J88: Lève une protection par action immédiate pendant l'action d'un adversaire. | L88: draft
A89: power.sv_double_warding | B89: class_power | C89: Double protection | D89: Double Warding | E89: official | F89: Complete Arcane | G89: sevenfold veil; defense | J89: Deux voiles pour une seule utilisation ; le moins puissant est à l'extérieur. | L89: draft
A90: power.sv_kaleidoscopic_doom | B90: class_power | C90: Fatalité kaléidoscopique | D90: Kaleidoscopic Doom | E90: official | F90: Complete Arcane | G90: sevenfold veil; dispel | I90: 1 | J90: Action simple, une créature à 18 m : dissipation suprême ciblée ; pour chaque sort dissipé, un voile (du rouge vers le violet) l'affecte comme si elle l'avait traversé. Équivaut à un sort du 9e niveau. | L90: draft
A91: bonus_type.ioun | B91: bonus_type | C91: Ioun | D91: Ioun | E91: team | F91: Équipe | G91: bonus type | J91: Type des bonus des pierres ioun. Se cumule avec l'altération ; deux bonus ioun sur la même valeur ne se cumulent pas. | L91: draft | M91: stacks = false
A92: bonus_type.template | B92: bonus_type | C92: Archétype | D92: Template | E92: team | F92: Équipe | G92: bonus type | J92: Bonus de caractéristiques des archétypes (Démon, Vampire, Dragon). Se cumulent entre eux. | L92: draft | M92: stacks = true ; sinon Int 2 + 4 + 2 ne s'additionneraient pas

Sheet Effects
A1: entity_id | B1: target | C1: op | D1: value | E1: bonus_type | F1: mult_mode | G1: layer | H1: condition | I1: scope | J1: status | K1: notes
A2: feat.example_feat | B2: ability.str.score | C2: add | D2: 4 | E2: morale | H2: active('toggle.rage') | I2: character | J2: draft | K2: Ligne d'exemple, ne pas importer
A3: feat.spell_focus_abjuration | B3: dc.school[abjuration] | C3: add | D3: 1 | E3: untyped | I3: character | J3: draft
A4: feat.greater_spell_focus_abjuration | B4: dc.school[abjuration] | C4: add | D4: 1 | E4: untyped | I4: character | J4: draft
A5: feat.skill_focus_spellcraft | B5: skill.spellcraft | C5: add | D5: 3 | E5: untyped | I5: character | J5: draft
A6: feat.continuum_comprehension | B6: skill.spellcraft | C6: add | D6: 2 | E6: untyped | I6: character | J6: draft
A7: feat.power_attack | B7: attack.melee | C7: add | D7: -@toggle.power_attack.value | E7: untyped | H7: active('toggle.power_attack') | I7: character | J7: draft | K7: Valeur choisie en début de tour
A8: feat.power_attack | B8: damage.melee | C8: add | D8: @toggle.power_attack.value * 2 | E8: untyped | H8: active('toggle.power_attack') | I8: character | J8: draft | K8: ×2 à deux mains
A9: feat.combat_expertise | B9: attack.melee | C9: add | D9: -@toggle.combat_expertise.value | E9: untyped | H9: active('toggle.combat_expertise') | I9: character | J9: draft | K9: Valeur choisie en début de tour, max 5
A10: feat.combat_expertise | B10: ac.total | C10: add | D10: @toggle.combat_expertise.value | E10: dodge | H10: active('toggle.combat_expertise') | I10: character | J10: draft | K10: Valeur choisie en début de tour, max 5
A11: feat.empower_spell | B11: spell.damage | C11: multiply | D11: 1.5 | F11: exclusive: metamagic_amplify | I11: spell | J11: draft | K11: Seul le plus fort du groupe s'applique
A12: feat.empower_spell | B12: spell.slot_cost | C12: add | D12: 2 | E12: untyped | I12: spell | J12: draft
A13: feat.quicken_spell | B13: spell.action | C13: set | D13: swift | G13: final | I13: spell | J13: draft
A14: feat.quicken_spell | B14: spell.slot_cost | C14: add | D14: 4 | E14: untyped | I14: spell | J14: draft
A15: feat.extend_spell | B15: spell.duration | C15: multiply | D15: 2 | F15: multiplicative | I15: spell | J15: draft
A16: feat.extend_spell | B16: spell.slot_cost | C16: add | D16: 1 | E16: untyped | I16: spell | J16: draft
A17: feat.persistent_spell | B17: spell.duration | C17: set | D17: 24h | G17: final | I17: spell | J17: draft
A18: feat.persistent_spell | B18: spell.slot_cost | C18: add | D18: 6 | E18: untyped | I18: spell | J18: to confirm
A19: feat.intensify_spell | B19: spell.damage | C19: multiply | D19: 2 | F19: exclusive: metamagic_amplify | I19: spell | J19: draft | K19: Seul le plus fort du groupe s'applique
A20: feat.intensify_spell | B20: spell.slot_cost | C20: add | D20: 6 | E20: untyped | I20: spell | J20: draft
A21: feat.superspell | B21: spell.numeric | C21: multiply | D21: 4 | F21: exclusive: metamagic_amplify | I21: spell | J21: draft | K21: Seul le plus fort du groupe s'applique
A22: feat.superspell | B22: spell.slot_cost | C22: add | D22: 9 | E22: untyped | I22: spell | J22: draft
A23: feat.improved_metamagic | B23: spell.slot_cost_per_modifier | C23: add | D23: -1 | E23: untyped | I23: spell | J23: draft | K23: Minimum +1 par modificateur
A24: feat.improved_spell_capacity | B24: slots.above_max | C24: add | D24: 1 | E24: untyped | I24: character | J24: draft | K24: Un emplacement au-dessus du maximum, par prise (×12)
A25: power.warblade_battle_clarity | B25: save.ref | C25: add | D25: @ability.int.mod | E25: untyped | I25: character | J25: to confirm | K25: Plafond ?
A26: power.warblade_battle_cunning | B26: damage.melee | C26: add | D26: @ability.int.mod | E26: untyped | I26: character | J26: draft
A27: power.warblade_battle_skill | B27: check.opposed | C27: add | D27: @ability.int.mod | E27: untyped | I27: character | J27: draft
A28: power.archmage_arcane_reach | B28: spell.range | C28: set | D28: 9 m | G28: final | H28: spell.range == 'touch' | I28: spell | J28: draft
A29: power.archmage_spell_power | B29: caster_level.arcane | C29: add | D29: 1 | E29: untyped | I29: character | J29: draft
A30: power.ultimate_magus_caster_level | B30: caster_level.arcane | C30: add | D30: 7 | E30: untyped | I30: character | J30: to confirm
A31: power.vt_beyond_grave_resilience | B31: hp.max | C31: add | D31: if(level('class.vt_grip_of_death') >= 7, 2000, if(level('class.vt_grip_of_death') >= 4, 1000, 500)) | E31: untyped | I31: character | J31: draft | K31: Paliers niveau 1 / 4 / 7 de la classe
A32: power.vt_master_of_death | B32: hp.regeneration | C32: add | D32: floor(@hp.max * if(level('class.vt_grip_of_death') >= 8, 15, if(level('class.vt_grip_of_death') >= 5, 10, 5)) / 100) | E32: untyped | H32: active('toggle.vt_grip_of_death') | I32: character | J32: draft
A33: power.vt_grip_of_death | B33: aura.damage_redirect_pct | C33: add | D33: if(level('class.vt_grip_of_death') >= 10, 15, if(level('class.vt_grip_of_death') >= 6, 10, 5)) | E33: untyped | H33: active('toggle.vt_grip_of_death') | I33: character | J33: draft | K33: Cumulatif avec d'autres effets
A34: power.vt_arcane_secret_spellcraft | B34: skill.spellcraft | C34: add | D34: if(level('class.vt_will_of_death') >= 7, 20, if(level('class.vt_will_of_death') >= 4, 10, 5)) | E34: untyped | I34: character | J34: draft | K34: Remplacement : 5, puis 10, puis 20
A35: class.vt_will_of_death | B35: caster_level.arcane | C35: add | D35: if(level('class.vt_will_of_death') >= 10, 15, if(level('class.vt_will_of_death') >= 5, 6, 3)) | E35: untyped | I35: character | J35: draft | K35: Remplacement : 3, puis 6, puis 15
A36: power.vt_mortis_incantatum | B36: spell.caster_level_vs_sr | C36: add | D36: 10 | E36: untyped | I36: spell | J36: draft
A37: power.vt_mortis_incantatum | B37: spell.dc | C37: add | D37: 10 | E37: untyped | I37: spell | J37: draft
A38: power.vt_primum_incantatum | B38: spell.damage | C38: multiply | D38: 3 | F38: multiplicative | I38: spell | J38: draft
A39: power.vt_primum_incantatum | B39: spell.healing | C39: multiply | D39: 2 | F39: multiplicative | I39: spell | J39: draft
A40: power.vt_primum_incantatum | B40: spell.duration | C40: multiply | D40: 2 | F40: multiplicative | I40: spell | J40: draft
A41: power.vt_primum_incantatum | B41: spell.area | C41: multiply | D41: 2 | F41: multiplicative | I41: spell | J41: draft
A42: power.vampire_bat_form | B42: speed.fly | C42: add | D42: 180 m | E42: untyped | H42: active('toggle.bat_form') | I42: character | J42: to confirm
A43: template.vampire | B43: weapon.threat_range | C43: add | D43: 3 | E43: untyped | I43: item | J43: to confirm | K43: Fiche : « 3 vampire »
A44: spell.bulls_strength | B44: ability.str.score | C44: add | D44: 4 | E44: enhancement | H44: active('toggle.bulls_strength') | I44: character | J44: draft | K44: ×4 avec Superspell = 16
A45: spell.bears_endurance | B45: ability.con.score | C45: add | D45: 4 | E45: enhancement | H45: active('toggle.bears_endurance') | I45: character | J45: draft | K45: ×4 avec Superspell = 16
A46: spell.foxs_cunning | B46: ability.int.score | C46: add | D46: 4 | E46: enhancement | H46: active('toggle.foxs_cunning') | I46: character | J46: draft | K46: ×4 avec Superspell = 16
A47: spell.divine_favor | B47: attack.all | C47: add | D47: max(min(floor(@caster_level / 3), 6), 1) | E47: luck | H47: active('toggle.divine_favor') | I47: character | J47: draft | K47: ×4 avec Superspell = 24
A48: spell.divine_favor | B48: damage.all | C48: add | D48: max(min(floor(@caster_level / 3), 6), 1) | E48: luck | H48: active('toggle.divine_favor') | I48: character | J48: draft | K48: ×4 avec Superspell = 24
A49: spell.barkskin | B49: ac.natural | C49: add | D49: min(2 + floor(max(@caster_level - 3, 0) / 3), 5) | E49: enhancement | H49: active('toggle.barkskin') | I49: character | J49: draft
A50: spell.protection_from_evil | B50: ac.total | C50: add | D50: 2 | E50: deflection | H50: active('toggle.protection_from_evil') | I50: character | J50: draft | K50: SRD ; fourni par l'Armure céleste
A51: spell.protection_from_evil | B51: save.all | C51: add | D51: 2 | E51: resistance | H51: vs evil | I51: character | J51: draft | K51: Situationnel
A52: spell.moonbow | B52: spell.damage | C52: dice | D52: 3 × 20d6 electricity | I52: spell | J52: draft | K52: Trois rayons
A53: spell.meteorite | B53: spell.damage | C53: dice | D53: 15 × 8d6 (½ bludgeoning, ½ fire) | I53: spell | J53: draft | K53: Rayon 12 m, pas de sauvegarde
A54: spell.heal_single | B54: spell.healing | C54: add | D54: min(15 * @caster_level, 375) | E54: untyped | I54: spell | J54: draft
A55: spell.heal_over_time | B55: spell.healing_per_round | C55: add | D55: 40 | E55: untyped | I55: spell | J55: draft
A56: item.blade_of_destruction | B56: weapon.attack | C56: add | D56: 12 | E56: enhancement | I56: item | J56: draft
A57: item.blade_of_destruction | B57: weapon.damage | C57: add | D57: 12 | E57: enhancement | I57: item | J57: draft
A58: item.blade_of_destruction | B58: weapon.threat_range | C58: add | D58: 3 | E58: untyped | I58: item | J58: draft | K58: 19-20 de base, +3 arme, +3 vampire = 13-20
A59: item.blade_of_destruction | B59: weapon.crit_multiplier | C59: set | D59: 8 | G59: base | I59: item | J59: draft
A60: item.celestial_armor | B60: ac.armor | C60: set | D60: 20 | G60: base | I60: character | J60: draft | K60: Harnois 8 + 12
A61: item.celestial_armor | B61: ac.dex_bonus | C61: max | D61: 10 | I61: character | J61: draft
A62: item.cloak_of_resistance_12 | B62: save.all | C62: add | D62: 12 | E62: resistance | I62: character | J62: draft
A63: item.trinket_critical | B63: weapon.threat_range | C63: add | D63: 4 | E63: untyped | I63: item | J63: draft
A64: item.trinket_critical | B64: weapon.crit_multiplier | C64: add | D64: 4 | E64: untyped | I64: item | J64: draft
A65: feat.spell_improvement | B65: caster_level.arcane | C65: add | D65: 4 | E65: untyped | I65: character | J65: to confirm | K65: Par prise ; ce don ne peut pas faire dépasser le niveau de personnage
A66: power.vt_epic_spell | B66: slots.above_max | C66: add | D66: 1 | E66: untyped | I66: character | J66: draft | K66: Par niveau qui l'accorde (1, 3, 5, 8, 10)
A67: spell.divine_power | B67: bab | C67: set | D67: if(level() <= 20, level(), 20 + floor(0.75 * (level() - 20))) | G67: base | H67: active('toggle.divine_power') | I67: character | J67: draft | K67: Règle maison ; 49 au niveau 59
A68: spell.spell_resistance | B68: spell_resistance | C68: set | D68: 12 + @caster_level.arcane | G68: base | H68: active('toggle.spell_resistance') | I68: character | J68: draft | K68: 72 avec niveau de lanceur 60
A69: spell.force_of_nature | B69: ability.str.score | C69: add | D69: 4 | E69: to confirm | H69: active('toggle.force_of_nature') | I69: character | J69: to confirm | K69: 16 avec Superspell
A70: spell.force_of_nature | B70: ability.dex.score | C70: add | D70: 4 | E70: to confirm | H70: active('toggle.force_of_nature') | I70: character | J70: to confirm | K70: 16 avec Superspell
A71: spell.force_of_nature | B71: ability.con.score | C71: add | D71: 4 | E71: to confirm | H71: active('toggle.force_of_nature') | I71: character | J71: to confirm | K71: 16 avec Superspell
A72: spell.giant_size | B72: ability.str.score | C72: add | D72: 32 | E72: size | H72: active('toggle.giant_size') | I72: character | J72: draft | K72: Taille C ; pas de Superspell
A73: spell.giant_size | B73: ability.con.score | C73: add | D73: 16 | E73: size | H73: active('toggle.giant_size') | I73: character | J73: draft | K73: Taille C ; pas de Superspell
A74: spell.force_of_colossus | B74: ability.str.score | C74: add | D74: 8 | E74: untyped | H74: active('toggle.force_of_colossus') | I74: character | J74: draft | K74: Bonus de taille, cumulé avec Taille de géant par accord du MJ ; 12 avec Empower
A75: spell.force_of_colossus | B75: ability.con.score | C75: add | D75: 4 | E75: untyped | H75: active('toggle.force_of_colossus') | I75: character | J75: draft | K75: Idem ; 6 avec Empower
A76: template.demon | B76: ability.int.score | C76: add | D76: 2 | E76: template | I76: character | J76: draft
A77: template.vampire | B77: ability.str.score | C77: add | D77: 8 | E77: template | I77: character | J77: draft
A78: template.vampire | B78: ability.con.score | C78: add | D78: 6 | E78: template | I78: character | J78: draft
A79: template.vampire | B79: ability.int.score | C79: add | D79: 4 | E79: template | I79: character | J79: draft
A80: template.vampire | B80: ability.cha.score | C80: add | D80: 2 | E80: template | I80: character | J80: draft
A81: template.dragon | B81: ability.all.score | C81: add | D81: 2 | E81: template | I81: character | J81: draft | K81: Les six caractéristiques
A82: race.danalieth | B82: ability.int.score | C82: add | D82: 2 | E82: racial | I82: character | J82: draft
A83: race.danalieth | B83: ability.cha.score | C83: add | D83: -2 | E83: racial | I83: character | J83: draft
A84: item.tomes | B84: ability.str.score | C84: add | D84: 5 | E84: inherent | I84: character | J84: draft
A85: item.tomes | B85: ability.con.score | C85: add | D85: 5 | E85: inherent | I85: character | J85: draft
A86: item.tomes | B86: ability.int.score | C86: add | D86: 5 | E86: inherent | I86: character | J86: draft
A87: item.tomes | B87: ability.cha.score | C87: add | D87: 5 | E87: inherent | I87: character | J87: draft
A88: item.ioun_stones | B88: ability.all.score | C88: add | D88: 2 | E88: ioun | I88: character | J88: draft | K88: Type ioun : se cumule avec l'altération
A89: item.blade_of_destruction | B89: weapon.damage | C89: dice | D89: 2d6 | I89: item | J89: draft | K89: Épée à deux mains
A90: spell.divine_power | B90: ability.str.score | C90: add | D90: 6 | E90: enhancement | H90: active('toggle.divine_power') | I90: character | J90: draft | K90: Ne se cumule pas avec Force du taureau (+16)
A91: spell.divine_power | B91: hp.temporary | C91: add | D91: level() | E91: untyped | H91: active('toggle.divine_power') | I91: character | J91: draft
A92: spell.force_of_colossus | B92: weapon.damage | C92: set | D92: 3d6 | G92: base | H92: active('toggle.force_of_colossus') | I92: item | J92: draft | K92: Arme taille G ; moyenne 10 (« Arme 10 » sur la fiche)
A93: power.ultimate_magus_arcane_spell_power | B93: caster_level.arcane | C93: add | D93: if(level('class.ultimate_magus') >= 20, 8, if(level('class.ultimate_magus') >= 18, 7, if(level('class.ultimate_magus') >= 15, 6, if(level('class.ultimate_magus') >= 12, 5, if(level('class.ultimate_magus') >= 10, 4, if(level('class.ultimate_magus') >= 7, 3, if(level('class.ultimate_magus') >= 4, 2, 1))))))) | E93: untyped | I93: character | J93: draft | K93: Livre : 1, 4, 7, 10 ; équipe : 12, 15, 18, 20
A94: power.vt_will_of_death_saves | B94: save.fort | C94: add | D94: 3.5 | E94: untyped | I94: character | J94: draft | K94: Valeur fixe pour retrouver la fiche ; à revoir si la classe progresse
A95: power.vt_will_of_death_saves | B95: save.ref | C95: add | D95: 3.5 | E95: untyped | I95: character | J95: draft | K95: Valeur fixe pour retrouver la fiche ; à revoir si la classe progresse
A96: power.vt_will_of_death_saves | B96: save.will | C96: add | D96: 3.5 | E96: untyped | I96: character | J96: draft | K96: Valeur fixe pour retrouver la fiche ; à revoir si la classe progresse
A97: spell.meteorite | B97: spell.area | C97: set | D97: radius 12 m | G97: base | I97: spell | J97: draft
A98: spell.meteorite | B98: spell.save | C98: set | D98: none | G98: base | I98: spell | J98: draft
A99: spell.heal_over_time | B99: spell.duration | C99: set | D99: min(@caster_level, 30) rounds | G99: base | I99: spell | J99: draft
A100: power.sv_unimpeachable_abjuration | B100: dc.dispel_own_abjuration | C100: add | D100: level('class.sevenfold_veil') | E100: untyped | I100: character | J100: draft | K100: +7 pour Danalieth
...

Sheet Progressions
A1: class_id | B1: level | C1: bab | D1: fort | E1: ref | F1: will | G1: grants | H1: status | I1: notes
A2: class.vt_grip_of_death | B2: 1 | C2: +0.5 | D2: +0.5 | E2: +0.5 | F2: +0.5 | G2: power.vt_grip_of_death (1) | H2: draft | I2: Classe épique : +½ par niveau
A3: class.vt_grip_of_death | B3: 2 | C3: +0.5 | D3: +0.5 | E3: +0.5 | F3: +0.5 | G3: power.vt_beyond_grave_resilience (1) | H3: draft | I3: Classe épique : +½ par niveau
A4: class.vt_grip_of_death | B4: 3 | C4: +0.5 | D4: +0.5 | E4: +0.5 | F4: +0.5 | G4: power.vt_master_of_death (1) | H4: draft | I4: Classe épique : +½ par niveau
A5: class.vt_grip_of_death | B5: 4 | C5: +0.5 | D5: +0.5 | E5: +0.5 | F5: +0.5 | G5: power.vt_beyond_grave_resilience (2) | H5: draft | I5: Classe épique : +½ par niveau
A6: class.vt_grip_of_death | B6: 5 | C6: +0.5 | D6: +0.5 | E6: +0.5 | F6: +0.5 | G6: power.vt_master_of_death (2) | H6: draft | I6: Classe épique : +½ par niveau
A7: class.vt_grip_of_death | B7: 6 | C7: +0.5 | D7: +0.5 | E7: +0.5 | F7: +0.5 | G7: power.vt_grip_of_death (2) | H7: draft | I7: Classe épique : +½ par niveau
A8: class.vt_grip_of_death | B8: 7 | C8: +0.5 | D8: +0.5 | E8: +0.5 | F8: +0.5 | G8: power.vt_beyond_grave_resilience (3) | H8: draft | I8: Classe épique : +½ par niveau
A9: class.vt_grip_of_death | B9: 8 | C9: +0.5 | D9: +0.5 | E9: +0.5 | F9: +0.5 | G9: power.vt_master_of_death (3) | H9: draft | I9: Classe épique : +½ par niveau
A10: class.vt_grip_of_death | B10: 9 | C10: +0.5 | D10: +0.5 | E10: +0.5 | F10: +0.5 | G10: bonus feat | H10: draft | I10: Classe épique : +½ par niveau
A11: class.vt_grip_of_death | B11: 10 | C11: +0.5 | D11: +0.5 | E11: +0.5 | F11: +0.5 | G11: power.vt_grip_of_death (3) | H11: draft | I11: Classe épique : +½ par niveau
A12: class.vt_will_of_death | B12: 1 | C12: +0.5 | D12: +0.5 | E12: +0.5 | F12: +0.5 | G12: caster level 3; power.vt_epic_spell | H12: draft | I12: Classe épique : +½ par niveau
A13: class.vt_will_of_death | B13: 2 | C13: +0.5 | D13: +0.5 | E13: +0.5 | F13: +0.5 | G13: power.vt_arcane_secret_spellcraft (+5) | H13: draft | I13: Classe épique : +½ par niveau
... A19: class.vt_will_of_death | B19: 8 | C19: +0.5 | D19: +0.5 | E19: +0.5 | F19: +0.5 | G19: power.vt_epic_spell | H19: draft | I19: Classe épique : +½ par niveau
A20: class.vt_will_of_death | B20: 9 | C20: +0.5 | D20: +0.5 | E20: +0.5 | F20: +0.5 | H20: draft | I20: Classe épique : +½ par niveau
A21: class.vt_will_of_death | B21: 10 | C21: +0.5 | D21: +0.5 | E21: +0.5 | F21: +0.5 | G21: caster level 15 (replaces 6); power.vt_epic_spell; power.vt_infinitum_incantatum | H21: draft | I21: Classe épique : +½ par niveau
A22: class.warblade | B22: 1 | C22: 1 | D22: 2 | E22: 0 | F22: 0 | G22: maneuvers; weapon aptitude | H22: to confirm | I22: Capacités d'après le livre, à vérifier
A23: class.warblade | B23: 2 | C23: 2 | D23: 3 | E23: 0 | F23: 0 | G23: power.warblade_battle_clarity; power.warblade_uncanny_dodge | H23: to confirm | I23: Capacités d'après le livre, à vérifier
A24: class.warblade | B24: 3 | C24: 3 | D24: 3 | E24: 1 | F24: 1 | H24: draft
A25: class.warblade | B25: 4 | C25: 4 | D25: 4 | E25: 1 | F25: 1 | H25: draft
A26: class.warblade | B26: 5 | C26: 5 | D26: 4 | E26: 1 | F26: 1 | G26: bonus feat | H26: to confirm | I26: Capacités d'après le livre, à vérifier
A27: class.warblade | B27: 6 | C27: 6 | D27: 5 | E27: 2 | F27: 2 | H27: draft
A28: class.warblade | B28: 7 | C28: 7 | D28: 5 | E28: 2 | F28: 2 | G28: battle ardor | H28: to confirm | I28: Capacités d'après le livre, à vérifier
A29: class.warblade | B29: 8 | C29: 8 | D29: 6 | E29: 2 | F29: 2 | H29: draft
A30: class.warblade | B30: 9 | C30: 9 | D30: 6 | E30: 3 | F30: 3 | G30: bonus feat; improved uncanny dodge | H30: to confirm | I30: Capacités d'après le livre, à vérifier
A31: class.warblade | B31: 10 | C31: 10 | D31: 7 | E31: 3 | F31: 3 | H31: draft
A32: class.warblade | B32: 11 | C32: 11 | D32: 7 | E32: 3 | F32: 3 | G32: power.warblade_battle_cunning | H32: to confirm | I32: Capacités d'après le livre, à vérifier
A33: class.warblade | B33: 12 | C33: 12 | D33: 8 | E33: 4 | F33: 4 | H33: draft
A34: class.warblade | B34: 13 | C34: 13 | D34: 8 | E34: 4 | F34: 4 | G34: bonus feat | H34: to confirm | I34: Capacités d'après le livre, à vérifier
A35: class.warblade | B35: 14 | C35: 14 | D35: 9 | E35: 4 | F35: 4 | H35: draft
A36: class.warblade | B36: 15 | C36: 15 | D36: 9 | E36: 5 | F36: 5 | G36: power.warblade_battle_skill | H36: to confirm | I36: Capacités d'après le livre, à vérifier
A37: class.warblade | B37: 16 | C37: 16 | D37: 10 | E37: 5 | F37: 5 | H37: draft
A38: class.warblade | B38: 17 | C38: 17 | D38: 10 | E38: 5 | F38: 5 | G38: bonus feat | H38: to confirm | I38: Capacités d'après le livre, à vérifier
A39: class.warblade | B39: 18 | C39: 18 | D39: 11 | E39: 6 | F39: 6 | H39: draft
A40: class.warblade | B40: 19 | C40: 19 | D40: 11 | E40: 6 | F40: 6 | G40: battle mastery | H40: to confirm | I40: Capacités d'après le livre, à vérifier
A41: class.warblade | B41: 20 | C41: 20 | D41: 12 | E41: 6 | F41: 6 | H41: draft
A42: rule.epic | B42: each level after 20 | C42: +0.5 | D42: +0.5 | E42: +0.5 | F42: +0.5 | G42: Règle maison : BBA et sauvegardes +½ par niveau épique, additionnés en fractions, arrondis une fois | H42: draft | I42: Retrouvé sur la fiche : total 39 / 29 / 35 / 29
A43: rule.hit_points | B43: each level | G43: Points de vie par niveau = ¾ du dé de vie (d12 → 9, d4 → 3) | H43: draft | I43: Retrouvé sur la fiche : 297 PV de base
A44: rule.experience | B44: level n | G44: XP requis = n × (n − 1) / 2 × 1000 | H44: draft | I44: 1 718 250 XP → niveau 59
A45: class.ultimate_magus | B45: 1 | C45: 0 | D45: 0 | E45: 0 | F45: 2 | G45: power.ultimate_magus_arcane_spell_power (+1); spellcasting: +1 level of lowest-caster-level arcane class | H45: draft | I45: Table du livre. Pris après le niveau 20 de personnage : BBA et sauvegardes suivent la règle épique (+½).
A46: class.ultimate_magus | B46: 2 | C46: 1 | D46: 0 | E46: 0 | F46: 3 | G46: power.ultimate_magus_expanded_knowledge (1st); spellcasting: +1 prepared and +1 spontaneous | H46: draft | I46: Table du livre. Pris après le niveau 20 de personnage : BBA et sauvegardes suivent la règle épique (+½).
A47: class.ultimate_magus | B47: 3 | C47: 1 | D47: 1 | E47: 1 | F47: 3 | G47: power.ultimate_magus_augmented_casting; spellcasting: +1 prepared and +1 spontaneous | H47: draft | I47: Table du livre. Pris après le niveau 20 de personnage : BBA et sauvegardes suivent la règle épique (+½).
A48: class.ultimate_magus | B48: 4 | C48: 2 | D48: 1 | E48: 1 | F48: 4 | G48: arcane spell power +2; expanded knowledge (2nd); spellcasting: +1 level of lowest-caster-level arcane class | H48: draft | I48: Table du livre. Pris après le niveau 20 de personnage : BBA et sauvegardes suivent la règle épique (+½).
A49: class.ultimate_magus | B49: 5 | C49: 2 | D49: 1 | E49: 1 | F49: 4 | G49: power.ultimate_magus_bonus_feat; spellcasting: +1 prepared and +1 spontaneous | H49: draft | I49: Table du livre. Pris après le niveau 20 de personnage : BBA et sauvegardes suivent la règle épique (+½).
A50: class.ultimate_magus | B50: 6 | C50: 3 | D50: 2 | E50: 2 | F50: 5 | G50: expanded knowledge (3rd); spellcasting: +1 prepared and +1 spontaneous | H50: draft | I50: Table du livre. Pris après le niveau 20 de personnage : BBA et sauvegardes suivent la règle épique (+½).
A51: class.ultimate_magus | B51: 7 | C51: 3 | D51: 2 | E51: 2 | F51: 5 | G51: arcane spell power +3; spellcasting: +1 level of lowest-caster-level arcane class | H51: draft | I51: Table du livre. Pris après le niveau 20 de personnage : BBA et sauvegardes suivent la règle épique (+½).
A52: class.ultimate_magus | B52: 8 | C52: 4 | D52: 2 | E52: 2 | F52: 6 | G52: expanded knowledge (4th); spellcasting: +1 prepared and +1 spontaneous | H52: draft | I52: Table du livre. Pris après le niveau 20 de personnage : BBA et sauvegardes suivent la règle épique (+½).
A53: class.ultimate_magus | B53: 9 | C53: 4 | D53: 3 | E53: 3 | F53: 6 | G53: power.ultimate_magus_bonus_feat; spellcasting: +1 prepared and +1 spontaneous | H53: draft | I53: Table du livre. Pris après le niveau 20 de personnage : BBA et sauvegardes suivent la règle épique (+½).
A54: class.ultimate_magus | B54: 10 | C54: 5 | D54: 3 | E54: 3 | F54: 7 | G54: arcane spell power +4; expanded knowledge (5th); spellcasting: +1 prepared and +1 spontaneous | H54: draft | I54: Table du livre. Pris après le niveau 20 de personnage : BBA et sauvegardes suivent la règle épique (+½).
A55: class.ultimate_magus | B55: 11 | G55: spellcasting +1 (+1 = lowest-caster-level class, +1 / +1 = both) | H55: draft | I55: Extension de l'équipe. BBA et sauvegardes : règle épique (+½)
A56: class.ultimate_magus | B56: 12 | G56: arcane spell power +5; spellcasting +1 / +1 (+1 = lowest-caster-level class, +1 / +1 = both) | H56: draft | I56: Extension de l'équipe. BBA et sauvegardes : règle épique (+½)
A57: class.ultimate_magus | B57: 13 | G57: power.ultimate_magus_bonus_feat; spellcasting +1 / +1 (+1 = lowest-caster-level class, +1 / +1 = both) | H57: draft | I57: Extension de l'équipe. BBA et sauvegardes : règle épique (+½)
A58: class.ultimate_magus | B58: 14 | G58: spellcasting +1 (+1 = lowest-caster-level class, +1 / +1 = both) | H58: draft | I58: Extension de l'équipe. BBA et sauvegardes : règle épique (+½)
A59: class.ultimate_magus | B59: 15 | G59: arcane spell power +6; spellcasting +1 / +1 (+1 = lowest-caster-level class, +1 / +1 = both) | H59: draft | I59: Extension de l'équipe. BBA et sauvegardes : règle épique (+½)
A60: class.ultimate_magus | B60: 16 | G60: power.ultimate_magus_bonus_feat; spellcasting +1 / +1 (+1 = lowest-caster-level class, +1 / +1 = both) | H60: draft | I60: Extension de l'équipe. BBA et sauvegardes : règle épique (+½)
A61: class.ultimate_magus | B61: 17 | G61: spellcasting +1 (+1 = lowest-caster-level class, +1 / +1 = both) | H61: draft | I61: Extension de l'équipe. BBA et sauvegardes : règle épique (+½)
A62: class.ultimate_magus | B62: 18 | G62: arcane spell power +7; spellcasting +1 / +1 (+1 = lowest-caster-level class, +1 / +1 = both) | H62: draft | I62: Extension de l'équipe. BBA et sauvegardes : règle épique (+½)
A63: class.ultimate_magus | B63: 19 | G63: power.ultimate_magus_bonus_feat; spellcasting +1 / +1 (+1 = lowest-caster-level class, +1 / +1 = both) | H63: draft | I63: Extension de l'équipe. BBA et sauvegardes : règle épique (+½)
A64: class.ultimate_magus | B64: 20 | G64: arcane spell power +8; power.ultimate_magus_augmented_casting_superior; spellcasting +1 / +1 (+1 = lowest-caster-level class, +1 / +1 = both) | H64: draft | I64: Extension de l'équipe. BBA et sauvegardes : règle épique (+½)
A65: class.sevenfold_veil | B65: 1 | C65: 0 | D65: 0 | E65: 0 | F65: 2 | G65: power.sv_warding (1/day); power.sv_unimpeachable_abjuration; power.sv_veil_red; spellcasting +1 existing arcane class (chosen) | H65: draft | I65: Table du livre. Pris après le niveau 20 : règle épique (+½).
A66: class.sevenfold_veil | B66: 2 | C66: 1 | D66: 0 | E66: 0 | F66: 3 | G66: power.sv_unanswerable_strike (+2); power.sv_veil_orange; spellcasting +1 existing arcane class (chosen) | H66: draft | I66: Table du livre. Pris après le niveau 20 : règle épique (+½).
A67: class.sevenfold_veil | B67: 3 | C67: 1 | D67: 1 | E67: 1 | F67: 3 | G67: warding 2/day; power.sv_veil_yellow; spellcasting +1 existing arcane class (chosen) | H67: draft | I67: Table du livre. Pris après le niveau 20 : règle épique (+½).
A68: class.sevenfold_veil | B68: 4 | C68: 2 | D68: 1 | E68: 1 | F68: 4 | G68: power.sv_reactive_warding; power.sv_veil_green; spellcasting +1 existing arcane class (chosen) | H68: draft | I68: Table du livre. Pris après le niveau 20 : règle épique (+½).
A69: class.sevenfold_veil | B69: 5 | C69: 2 | D69: 1 | E69: 1 | F69: 4 | G69: warding 3/day; power.sv_veil_blue; spellcasting +1 existing arcane class (chosen) | H69: draft | I69: Table du livre. Pris après le niveau 20 : règle épique (+½).
A70: class.sevenfold_veil | B70: 6 | C70: 3 | D70: 2 | E70: 2 | F70: 5 | G70: unanswerable strike +4; power.sv_double_warding; power.sv_veil_indigo; spellcasting +1 existing arcane class (chosen) | H70: draft | I70: Table du livre. Pris après le niveau 20 : règle épique (+½).
A71: class.sevenfold_veil | B71: 7 | C71: 3 | D71: 2 | E71: 2 | F71: 5 | G71: power.sv_kaleidoscopic_doom; power.sv_veil_violet; warding 4/day; spellcasting +1 existing arcane class (chosen) | H71: draft | I71: Table du livre. Pris après le niveau 20 : règle épique (+½).

Sheet Relations
A1: from_id | B1: relation | C1: to_id | D1: level | E1: notes
A2: class.archmage | B2: grants | C2: power.archmage_mastery_of_shaping | E2: Choix de haute arcane
A3: class.archmage | B3: grants | C3: power.archmage_mastery_of_elements | E3: Choix de haute arcane
A4: class.archmage | B4: grants | C4: power.archmage_mastery_of_counterspelling | E4: Choix de haute arcane
A5: class.archmage | B5: grants | C5: power.archmage_arcane_reach | E5: Choix de haute arcane
A6: class.archmage | B6: grants | C6: power.archmage_spell_power | E6: Choix de haute arcane
A7: class.ultimate_magus | B7: grants | C7: power.ultimate_magus_caster_level
A8: template.vampire | B8: grants | C8: power.vampire_bat_form
A9: template.vampire | B9: grants | C9: power.vampire_house_rules
A10: feat.greater_spell_focus_abjuration | B10: requires | C10: feat.spell_focus_abjuration
A11: spell.bulls_strength | B11: on_spell_list | C11: class.wizard | D11: 2 | E11: SRD
A12: spell.bulls_strength | B12: on_spell_list | C12: class.sorcerer | D12: 2 | E12: SRD
A13: spell.bears_endurance | B13: on_spell_list | C13: class.wizard | D13: 2 | E13: SRD
A14: spell.foxs_cunning | B14: on_spell_list | C14: class.wizard | D14: 2 | E14: SRD
A15: spell.barkskin | B15: on_spell_list | C15: class.wizard | E15: to confirm : sort de druide/rôdeur dans le SRD, pas de magicien
A16: spell.divine_favor | B16: on_spell_list | C16: class.wizard | E16: to confirm : sort de prêtre/paladin dans le SRD
A17: spell.protection_from_evil | B17: on_spell_list | C17: class.wizard | D17: 1 | E17: SRD
A18: class.ultimate_magus | B18: grants | C18: power.ultimate_magus_augmented_casting_superior | D18: 20 | E18: Extension de l'équipe
A19: class.warblade | B19: grants | C19: power.warblade_uncanny_dodge | D19: 2
A20: spell.divine_power | B20: on_spell_list | C20: class.wizard | E20: to confirm : sort de prêtre dans le SRD
A21: spell.spell_resistance | B21: on_spell_list | C21: class.wizard | E21: to confirm : sort de prêtre dans le SRD
A22: class.sevenfold_veil | B22: grants | C22: power.sv_warding
A23: class.sevenfold_veil | B23: grants | C23: power.sv_unimpeachable_abjuration
A24: class.sevenfold_veil | B24: grants | C24: power.sv_unanswerable_strike
A25: class.sevenfold_veil | B25: grants | C25: power.sv_reactive_warding
A26: class.sevenfold_veil | B26: grants | C26: power.sv_double_warding
A27: class.sevenfold_veil | B27: grants | C27: power.sv_kaleidoscopic_doom
A28: class.sevenfold_veil | B28: grants | C28: power.sv_veil_red
A29: class.sevenfold_veil | B29: grants | C29: power.sv_veil_orange
A30: class.sevenfold_veil | B30: grants | C30: power.sv_veil_yellow
A31: class.sevenfold_veil | B31: grants | C31: power.sv_veil_green
A32: class.sevenfold_veil | B32: grants | C32: power.sv_veil_blue
A33: class.sevenfold_veil | B33: grants | C33: power.sv_veil_indigo
A34: class.sevenfold_veil | B34: grants | C34: power.sv_veil_violet
A35: spell.moonbow | B35: on_spell_list | C35: class.wizard | D35: 9 | E35: to confirm : liste supposée
A36: spell.moonbow | B36: on_spell_list | C36: class.sorcerer | D36: 9 | E36: to confirm : liste supposée
A37: spell.meteorite | B37: on_spell_list | C37: class.wizard | D37: 9 | E37: to confirm : liste supposée
A38: spell.meteorite | B38: on_spell_list | C38: class.sorcerer | D38: 9 | E38: to confirm : liste supposée

Sheet Danalieth abilities
A1: Ability | B1: Base | C1: Race | D1: Level | E1: Demon | F1: Vampire | G1: Dragon | H1: Tome | I1: Ioun | J1: Enhancement (spell) | K1: Force of the colossus | L1: Force of nature | M1: Giant size | N1: Total | O1: Modifier | P1: Sheet total | Q1: Check
A2: Strength | B2: 18 | F2: 8 | G2: 2 | H2: 5 | I2: 2 | J2: 16 | K2: 12 | L2: 16 | M2: 32 | N2: =SUM(B2:M2) -> 111 | O2: =ROUNDDOWN((N2-10)/2,0) -> 50 | P2: 111 | Q2: =IF(N2=P2,"OK","MISMATCH") -> OK
A3: Dexterity | B3: 16 | G3: 2 | I3: 2 | L3: 16 | N3: =SUM(B3:M3) -> 36 | O3: =ROUNDDOWN((N3-10)/2,0) -> 13 | P3: 36 | Q3: =IF(N3=P3,"OK","MISMATCH") -> OK
A4: Constitution | B4: 16 | F4: 6 | G4: 2 | H4: 5 | I4: 2 | J4: 16 | K4: 6 | L4: 16 | M4: 16 | N4: =SUM(B4:M4) -> 85 | O4: =ROUNDDOWN((N4-10)/2,0) -> 37 | P4: 85 | Q4: =IF(N4=P4,"OK","MISMATCH") -> OK
A5: Intelligence | B5: 18 | C5: 2 | D5: 14 | E5: 2 | F5: 4 | G5: 2 | H5: 5 | I5: 2 | J5: 16 | N5: =SUM(B5:M5) -> 65 | O5: =ROUNDDOWN((N5-10)/2,0) -> 27 | P5: 65 | Q5: =IF(N5=P5,"OK","MISMATCH") -> OK
A6: Wisdom | B6: 12 | G6: 2 | I6: 2 | N6: =SUM(B6:M6) -> 16 | O6: =ROUNDDOWN((N6-10)/2,0) -> 3 | P6: 16 | Q6: =IF(N6=P6,"OK","MISMATCH") -> OK
A7: Charisma | B7: 12 | C7: -2 | F7: 2 | G7: 2 | H7: 5 | I7: 2 | N7: =SUM(B7:M7) -> 21 | O7: =ROUNDDOWN((N7-10)/2,0) -> 5 | P7: 21 | Q7: =IF(N7=P7,"OK","MISMATCH") -> OK
A9: Enhancement column: Bull's Strength, Bear's Endurance, Fox's Cunning (+4 × 4 with Superspell). Each column is one bonus type. Blue = values from the sheet; black = formulas.

Sheet Danalieth checks
A1: Value | B1: Component 1 | C1: Component 2 | D1: Component 3 | E1: Component 4 | F1: Component 5 | G1: Component 6 | H1: Component 7 | I1: Computed | J1: Sheet | K1: Check | L1: How
A2: Character level | B2: 20 | C2: 3 | D2: 1 | E2: 5 | F2: 7 | G2: 20 | H2: 3 | I2: =SUM(B2:H2) -> 59 | J2: 59 | K2: =IF(I2=J2,"OK","MISMATCH") -> OK | L2: Warblade, Wizard, Sorcerer, Archmage, Sevenfold Veil, Ultimate Magus, Will of Death
A3: Base attack (classes) | B3: 20 | C3: 1.5 | D3: 0.5 | E3: 2.5 | F3: 3.5 | G3: 10 | H3: 1.5 | I3: =ROUNDDOWN(SUM(B3:H3),0) -> 39 | J3: 39 | K3: =IF(I3=J3,"OK","MISMATCH") -> OK | L3: 20 + ½ par niveau épique, arrondi une fois
A4: Base attack (Divine Power) | B4: =I2 -> 59 | C4: 20 | D4: 0.75 | I4: =C4+ROUNDDOWN(D4*(B4-20),0) -> 49 | J4: 49 | K4: =IF(I4=J4,"OK","MISMATCH") -> OK | L4: 20 + 0,75 par niveau au-delà de 20
A5: Reflex (class) | B5: 6 | C5: 1.5 | D5: 0.5 | E5: 2.5 | F5: 3.5 | G5: 10 | H5: =1.5+3.5 -> 5 | I5: =ROUNDDOWN(SUM(B5:H5),0) -> 29 | J5: 29 | K5: =IF(I5=J5,"OK","MISMATCH") -> OK | L5: Volonté de la mort : 1,5 (épique) + 3,5 (Résistance de l'émissaire)
A6: Fortitude (class) | B6: 12 | C6: 1.5 | D6: 0.5 | E6: 2.5 | F6: 3.5 | G6: 10 | H6: =1.5+3.5 -> 5 | I6: =ROUNDDOWN(SUM(B6:H6),0) -> 35 | J6: 35 | K6: =IF(I6=J6,"OK","MISMATCH") -> OK | L6: Volonté de la mort : 1,5 (épique) + 3,5 (Résistance de l'émissaire)
A7: Will (class) | B7: 6 | C7: 1.5 | D7: 0.5 | E7: 2.5 | F7: 3.5 | G7: 10 | H7: =1.5+3.5 -> 5 | I7: =ROUNDDOWN(SUM(B7:H7),0) -> 29 | J7: 29 | K7: =IF(I7=J7,"OK","MISMATCH") -> OK | L7: Volonté de la mort : 1,5 (épique) + 3,5 (Résistance de l'émissaire)
A8: Reflex (total) | B8: =I5 -> 29 | C8: ='Danalieth abilities'!O3 -> 13 | D8: ='Danalieth abilities'!O5 -> 27 | E8: 12 | I8: =SUM(B8:E8) -> 81 | J8: 81 | K8: =IF(I8=J8,"OK","MISMATCH") -> OK | L8: Classes + Dex + Int (Clarté du combat) + cape
A9: Fortitude (total) | B9: =I6 -> 35 | C9: ='Danalieth abilities'!O4 -> 37 | D9: 12 | I9: =SUM(B9:D9) -> 84 | J9: 84 | K9: =IF(I9=J9,"OK","MISMATCH") -> OK | L9: Classes + Con + cape
A10: Will (total) | B10: =I7 -> 29 | C10: ='Danalieth abilities'!O6 -> 3 | D10: 12 | I10: =SUM(B10:D10) -> 44 | J10: 44 | K10: =IF(I10=J10,"OK","MISMATCH") -> OK | L10: Classes + Sag + cape
A11: Base hit points | B11: 180 | C11: 9 | D11: 3 | E11: 15 | F11: 21 | G11: 60 | H11: 9 | I11: =SUM(B11:H11) -> 297 | J11: 297 | K11: =IF(I11=J11,"OK","MISMATCH") -> OK | L11: ¾ du dé de vie par niveau
A12: Total hit points | B12: =I11 -> 297 | C12: ='Danalieth abilities'!O4 -> 37 | D12: =I2 -> 59 | I12: =B12+C12*D12 -> 2480 | J12: 2480 | K12: =IF(I12=J12,"OK","MISMATCH") -> OK | L12: Base + mod. Con × niveau
A13: Melee attack | B13: =I4 -> 49 | C13: 24 | D13: 12 | E13: 10 | F13: ='Danalieth abilities'!O2 -> 50 | I13: =SUM(B13:F13) -> 145 | J13: 145 | K13: =IF(I13=J13,"OK","MISMATCH") -> OK | L13: BBA (Puissance divine) + Faveur divine + arme + posture + mod. Force
A14: Melee damage | B14: =ROUNDDOWN(3*3.5,0) -> 10 | C14: 12 | D14: =ROUNDDOWN('Danalieth abilities'!O2*1.5,0) -> 75 | E14: 24 | F14: ='Danalieth abilities'!O5 -> 27 | I14: =SUM(B14:F14) -> 148 | J14: 148 | K14: =IF(I14=J14,"OK","MISMATCH") -> OK | L14: Arme 3d6 (taille G, moyenne 10) + altération + Force × 1,5 + Faveur divine + mod. Int
A15: Spell resistance | B15: 12 | C15: 60 | I15: =B15+C15 -> 72 | J15: 72 | K15: =IF(I15=J15,"OK","MISMATCH") -> OK | L15: Résistance à la magie : 12 + niveau de lanceur
A16: Level from XP | B16: 1718250 | I16: =ROUNDDOWN((1+SQRT(1+8*B16/1000))/2,0) -> 59 | J16: 59 | K16: =IF(I16=J16,"OK","MISMATCH") -> OK | L16: n × (n − 1) / 2 × 1000 ≤ XP
A18: Blue = numbers from the sheet; black = formulas (modifiers come from the Danalieth abilities tab). Check must read OK on every row.
